diff-highlight-tokens
setup.cfg
setup.py
diff_highlight_tokens.egg-info/PKG-INFO
diff_highlight_tokens.egg-info/SOURCES.txt
diff_highlight_tokens.egg-info/dependency_links.txt
diff_highlight_tokens.egg-info/requires.txt
diff_highlight_tokens.egg-info/top_level.txt
diff_highlighter/__init__.py
diff_highlighter/constants.py
diff_highlighter/diff.py
diff_highlighter/main.py
diff_highlighter/utils.py
diff_highlighter/working_with_tokens.py